databricks_helper
databricks_helper\api
databricks_helper\api\src
