Metadata-Version: 2.1
Name: databricks-helper
Version: 0.0.1
Summary: databricks helper package
Home-page: https://github.com/SamuelJansen/databricks-helper/
Download-URL: https://github.com/SamuelJansen/databricks-helper/archive/v0.0.1.tar.gz
Author: Samuel Jansen
Author-email: samuel.jansenn@gmail.com
License: MIT
Keywords: helper,databricks helper package,databricks helper,helper package
Classifier: Development Status :: 3 - Alpha
Classifier: Intended Audience :: Developers
Classifier: Topic :: Software Development :: Build Tools
Classifier: License :: OSI Approved :: MIT License
Classifier: Programming Language :: Python :: 3.7
Requires-Python: >=3.7
License-File: LICENSE
